GOArbf/__init__.py
GOArbf/GOMORS2/__init__.py
GOArbf/GOMORS2/archiving_strategies.py
GOArbf/GOMORS2/gomors_adaptive_sampling.py
GOArbf/GOMORS2/gomors_moea_problem.py
GOArbf/GOMORS2/gomors_sync_strategies.py
GOArbf/GOMORS2/hv.py
GOArbf/GOMORS2/mo_utils.py
GOArbf/GOMORS2/selection_rules.py
GOArbf/GOMORS2/simple_experiment.py
GOArbf/GOMORS2/test_problems.py
GOArbf/GOMORS2/water_experiments.py
GOArbf/GOPS2/BBOB.py
GOArbf/GOPS2/__init__.py
GOArbf/GOPS2/bbobbenchmarks.py
GOArbf/GOPS2/experiments_on_test_problems.py
GOArbf/GOPS2/gops_hybrid_strategies.py
GOArbf/GOPS2/sop_utils.py
GOArbf/MRSO2/Compare_RBF_DYCORS.py
GOArbf/MRSO2/MFB.py
GOArbf/MRSO2/MFO_main.py
GOArbf/MRSO2/MFO_main_mpi.py
GOArbf/MRSO2/MFO_main_mpi_optimizer.py
GOArbf/MRSO2/MFO_main_parallel.py
GOArbf/MRSO2/PDT.py
GOArbf/MRSO2/Read_Data.py
GOArbf/MRSO2/__init__.py
GOArbf/MRSO2/cluster-k-means.py
GOArbf/MRSO2/de.py
GOArbf/MRSO2/deprecation.py
GOArbf/MRSO2/draw_process.py
GOArbf/MRSO2/generate_fixed_sample_points.py
GOArbf/MRSO2/gpr.py
GOArbf/MRSO2/heuristic_methods.py
GOArbf/MRSO2/kernels.py
GOArbf/MRSO2/modified_adaptive_sampling.py
GOArbf/MRSO2/modified_gp_regression.py
GOArbf/MRSO2/modified_merit_functions.py
GOArbf/MRSO2/modified_sot_sync_strategies.py
GOArbf/MRSO2/modified_test_problems.py
GOArbf/MRSO2/new_main.py
GOArbf/MRSO2/prediction_distance_definitions.py
GOArbf/MRSO2/push_to_boundary.py
GOArbf/MRSO2/pyds.py
GOArbf/MRSO2/surface3d_demo.py
GOArbf/MRSO2/test.py
GOArbf/MRSO2/gp_extras/__init__.py
GOArbf/MRSO2/gp_extras/kernels/__init__.py
GOArbf/MRSO2/gp_extras/kernels/kernels_non_stationary.py
GOArbf/epsMaSO2/__init__.py
GOArbf/epsMaSO2/archiving_strategies.py
GOArbf/epsMaSO2/gomors_adaptive_sampling.py
GOArbf/epsMaSO2/gomors_moea_problem.py
GOArbf/epsMaSO2/gomors_sync_strategies.py
GOArbf/epsMaSO2/hv.py
GOArbf/epsMaSO2/mo_utils.py
GOArbf/epsMaSO2/multiobjective_problems.py
GOArbf/epsMaSO2/multiple_experiments.py
GOArbf/epsMaSO2/selection_rules.py
GOArbf/optimize/__init__.py
GOArbf-0.0.1.dist-info/LICENSE.rst
GOArbf-0.0.1.dist-info/METADATA
GOArbf-0.0.1.dist-info/WHEEL
GOArbf-0.0.1.dist-info/top_level.txt
GOArbf-0.0.1.dist-info/RECORD
