Metadata-Version: 2.1
Name: GOArbf
Version: 0.0.1
Summary: Global Optimization Algorithms with RBF Surrogates
Home-page: https://github.com/Katherine-NUS/surrogate-optimization
Author: Zhou Xiaoqian
Author-email: zhouxiaoqian@u.nus.edu
License: LICENSE.rst
Classifier: Intended Audience :: Science/Research
Classifier: Programming Language :: Python
Classifier: Topic :: Scientific/Engineering
Classifier: Operating System :: Microsoft :: Windows
Classifier: Operating System :: POSIX
Classifier: Operating System :: Unix
Classifier: Operating System :: MacOS
Classifier: Programming Language :: Python :: 3.4
Classifier: Programming Language :: Python :: 3.5
Classifier: Programming Language :: Python :: 3.6
Classifier: Programming Language :: Python :: 3.7
License-File: LICENSE.rst
Requires-Dist: pysot
